{
    "accounts": [
        {
            "id": 1,
            "name": "Wade Warren",
            "Order_no": 15478256,
            "Amount": "$124.00",
            "Status": "Delivered",
            "imageURL": "pexels-abolfazl-salehi-479650199-16233575.jpg"
        },
        {
            "id": 2,
            "name": "Jane Cooper",
            "Order_no": 48965786,
            "Amount": "$365.02",
            "Status": "Delivered",
            "imageURL": "pexels-behrouz-sasani-3568050-18635149.jpg"
        },
        {
            "id": 3,
            "name": "Guy Hawkins",
            "Order_no": 78958215,
            "Amount": "$45.88",
            "Status": "Cancelled",
            "imageURL": "pexels-brunocortes1969-29765330.jpg"
        },
        {
            "id": 4,
            "name": "Kristin Watson",
            "Order_no": 20965732,
            "Amount": "$65.00",
            "Status": "Pending",
            "imageURL": "pexels-abolfazl-salehi-479650199-16233575.jpg"
        },
        {
            "id": 5,
            "name": "Cody Fisher",
            "Order_no": 95715620,
            "Amount": "$545.00",
            "Status": "Delivered",
            "imageURL": "pexels-emilygarland-1499327.jpg"
        }
    ]
}